{
    "source": 0,
    "enable_heatmap": true,
    "enable_flow": false,
    "enable_reconstruction": false,
    "display_3d": false,
    "save_raw": true,
    "save_contact": false,
    "save_mask": false,
    "save_flow": false,
    "save_height_3d": false,
    "save_height_2d": false,
    "frame_scale": 0.2,
    "capture_mode": "Image",
    "auto_capture_threshold": 500,
    "invert_depth": false,
    "depth_scale": 8.0,
    "grid_res": 40,
    "blur_size": 9,
    "diff_method": "Texture Contrast Difference (TCD)",
    "abs_thresh": 0.08,
    "abs_blur": 9,
    "grad_thresh": 0.05,
    "grad_ksize": 5,
    "lab_thresh": 0.06,
    "lab_wL": 1.0,
    "lab_wAB": 1.0,
    "otsu_correct": 1.0,
    "hsv_thresh": 0.08,
    "hsv_wH": 1.2,
    "hsv_wS": 0.8,
    "hsv_wV": 0.5,
    "tcd_thresh": 0.06,
    "tcd_ksize": 7,
    "vector_scale": 2.5,
    "vector_min_mag": 1.5,
    "normalize_flow": false,
    "object_cutoff": 0.0,
    "gain_R": 1.0,
    "gain_G": 1.0,
    "gain_B": 1.0,
    "crosstalk_R2B": 0.0,
    "crosstalk_G2B": 0.0,
    "bias_gx": 0.0,
    "bias_gy": 0.0,
    "detrend_kernel": 0,
    "w_xR": 1.5,
    "w_xG": -1.5,
    "w_xB": 0.0,
    "w_yR": 0.0,
    "w_yG": 0.0,
    "w_yB": 1.5,
    "enable_raw": true,
    "layout_cols": "1"
}